README.md
setup.py
Nuphy.egg-info/PKG-INFO
Nuphy.egg-info/SOURCES.txt
Nuphy.egg-info/dependency_links.txt
Nuphy.egg-info/top_level.txt
bin/nuphy
nuphy/__init__.py
nuphy/compounds.py
nuphy/fispact.py
nuphy/fispact_input.py
nuphy/helps.py
nuphy/kinematics.py
nuphy/main.py
nuphy/nubase.py
nuphy/rolfs.py
nuphy/spectra.py
nuphy/sr.py
nuphy/srim.py
nuphy/data/libs2013.tgz
nuphy/data/nubase.mas12
nuphy/data/nubase2016.txt
nuphy/unit1/__init__.py
nuphy/unit1/unit1.py
test/__init__.py
test/test_nubase.py
test/test_one.py