Metadata-Version: 2.1
Name: Nuphy
Version: 0.2.17
Summary: Nuclear Physics multitool: reaction kinematics, wrapper: srim,...
Home-page: http://spiral2.cz
Author: Jaromir Mrazek
Author-email: me@example.com
License: UNKNOWN
Platform: UNKNOWN
